dnv/net/stubs.py
dnv_net_intellisense-1.0.0.dist-info/LICENSE
dnv_net_intellisense-1.0.0.dist-info/METADATA
dnv_net_intellisense-1.0.0.dist-info/WHEEL
dnv_net_intellisense-1.0.0.dist-info/entry_points.txt
dnv_net_intellisense-1.0.0.dist-info/top_level.txt
dnv_net_intellisense-1.0.0.dist-info/RECORD
