Metadata-Version: 2.1
Name: dnv-net-intellisense
Version: 1.0.0
Summary: IntelliSense support for the `with` statement for dotnet runtime assemblies from Python.
Author-email: DNV AS <software.support@dnv.com>
License: MIT License
Keywords: dotnet,dotnetruntime,netruntime,net.runtime
Classifier: License :: OSI Approved :: MIT License
Requires-Python: >=3.10
License-File: LICENSE
